[
    {
        "coords": [-45.56791, -130.001221],
        "description": "On top of the airvent",
        "image_url": "",
        "video_id": "UtroQkgbPnQ",
        "video_timestamp": 71,
        "display_name": "LD Organics Product N. 1"
    },
    {
        "coords": [-42.236652, -115.686035],
        "description": "On the energy control panel",
        "image_url": "",
        "video_id": "UtroQkgbPnQ",
        "video_timestamp": 110,
        "display_name": "LD Organics Product N. 2"
    },
    {
        "coords": [-28.478349, -112.972412],
        "description": "Inside the security cabin",
        "image_url": "",
        "video_id": "UtroQkgbPnQ",
        "video_timestamp": 150,
        "display_name": "LD Organics Product N. 3"
    },
    {
        "coords": [-33.063924, -101.206055],
        "description": "On the left hand side of the boat, on top of a fire hose",
        "image_url": "",
        "video_id": "UtroQkgbPnQ",
        "video_timestamp": 184,
        "display_name": "LD Organics Product N. 4"
    },
    {
        "coords": [-31.924193, -85.583496],
        "description": "Inside the security cabin",
        "image_url": "",
        "video_id": "UtroQkgbPnQ",
        "video_timestamp": 231,
        "display_name": "LD Organics Product N. 5"
    },
    {
        "coords": [-41.869561, -88.560791],
        "description": "On the boat's tool chest",
        "image_url": "",
        "video_id": "UtroQkgbPnQ",
        "video_timestamp": 271,
        "display_name": "LD Organics Product N. 6"
    },
    {
        "coords": [-36.923548, -77.475586],
        "description": "On the trashcan under the bridge",
        "image_url": "",
        "video_id": "UtroQkgbPnQ",
        "video_timestamp": 314,
        "display_name": "LD Organics Product N. 7"
    },
    {
        "coords": [-35.791083, -67.17041],
        "description": "Inside the pipes laid flat",
        "image_url": "",
        "video_id": "UtroQkgbPnQ",
        "video_timestamp": 357,
        "display_name": "LD Organics Product N. 8"
    },
    {
        "coords": [-22.075459, -65.709229],
        "description": "On the brick wall next the pipes",
        "image_url": "",
        "video_id": "UtroQkgbPnQ",
        "video_timestamp": 392,
        "display_name": "LD Organics Product N. 9"
    },
    {
        "coords": [-18.271086, -75.234375],
        "description": "On the brick wall between the entrance of the hospital and the broken brick wall",
        "image_url": "",
        "video_id": "UtroQkgbPnQ",
        "video_timestamp": 432,
        "display_name": "LD Organics Product N. 10"
    },
    {
        "coords": [-23.63446, -77.926025],
        "description": "On the ran down forklift",
        "image_url": "",
        "video_id": "UtroQkgbPnQ",
        "video_timestamp": 473,
        "display_name": "LD Organics Product N. 11"
    },
    {
        "coords": [-22.553147, -93.153076],
        "description": "On the roof of the building",
        "image_url": "",
        "video_id": "UtroQkgbPnQ",
        "video_timestamp": 509,
        "display_name": "LD Organics Product N. 12"
    },
    {
        "coords": [-20.13847, -103.425293],
        "description": "On the park's benches",
        "image_url": "",
        "video_id": "UtroQkgbPnQ",
        "video_timestamp": 553,
        "display_name": "LD Organics Product N. 13"
    },
    {
        "coords": [-20.324024, -107.687988],
        "description": "On the metal bars under the bridge",
        "image_url": "",
        "video_id": "UtroQkgbPnQ",
        "video_timestamp": 588,
        "display_name": "LD Organics Product N. 14"
    },
    {
        "coords": [-15.284185, -103.743896],
        "description": "On the roof, on the edge, next to the air vent",
        "image_url": "",
        "video_id": "UtroQkgbPnQ",
        "video_timestamp": 633,
        "display_name": "LD Organics Product N. 15"
    },
    {
        "coords": [-8.428904, -99.645996],
        "description": "On the metal pipes laid flat at the ground floor",
        "image_url": "",
        "video_id": "UtroQkgbPnQ",
        "video_timestamp": 672,
        "display_name": "LD Organics Product N. 16"
    },
    {
        "coords": [-12.554564, -98.668213],
        "description": "Under the bridge, under the vinewood graffiti",
        "image_url": "",
        "video_id": "UtroQkgbPnQ",
        "video_timestamp": 707,
        "display_name": "LD Organics Product N. 17"
    },
    {
        "coords": [-14.562318, -91.867676],
        "description": "On the airvent, at the lowest roof's height",
        "image_url": "",
        "video_id": "UtroQkgbPnQ",
        "video_timestamp": 753,
        "display_name": "LD Organics Product N. 18"
    },
    {
        "coords": [-14.455958, -87.06665],
        "description": "Inside the ran down bus",
        "image_url": "",
        "video_id": "UtroQkgbPnQ",
        "video_timestamp": 791,
        "display_name": "LD Organics Product N. 19"
    },
    {
        "coords": [-3.93002, -80.804443],
        "description": "On an airvent on the roof",
        "image_url": "",
        "video_id": "UtroQkgbPnQ",
        "video_timestamp": 835,
        "display_name": "LD Organics Product N. 20"
    },
    {
        "coords": [0.549308, -87.637939],
        "description": "Inside the ran down bus",
        "image_url": "",
        "video_id": "UtroQkgbPnQ",
        "video_timestamp": 874,
        "display_name": "LD Organics Product N. 21"
    },
    {
        "coords": [0.472407, -94.559326],
        "description": "Inside of the sewers",
        "image_url": "",
        "video_id": "UtroQkgbPnQ",
        "video_timestamp": 913,
        "display_name": "LD Organics Product N. 22"
    },
    {
        "coords": [-3.688855, -102.095947],
        "description": "On the plant's pot",
        "image_url": "",
        "video_id": "UtroQkgbPnQ",
        "video_timestamp": 986,
        "display_name": "LD Organics Product N. 23"
    },
    {
        "coords": [-5.473832, -109.072266],
        "description": "On the brick wall for the plants",
        "image_url": "",
        "video_id": "UtroQkgbPnQ",
        "video_timestamp": 1024,
        "display_name": "LD Organics Product N. 24"
    },
    {
        "coords": [-2.910125, -115.773926],
        "description": "On the park's banquette",
        "image_url": "",
        "video_id": "UtroQkgbPnQ",
        "video_timestamp": 1061,
        "display_name": "LD Organics Product N. 25"
    },
    {
        "coords": [-4.477856, -117.828369],
        "description": "On the trashcan up the stairs",
        "image_url": "",
        "video_id": "UtroQkgbPnQ",
        "video_timestamp": 1095,
        "display_name": "LD Organics Product N. 26"
    },
    {
        "coords": [-7.024572, -116.993408],
        "description": "Under the wooden stairs",
        "image_url": "",
        "video_id": "UtroQkgbPnQ",
        "video_timestamp": 1134,
        "display_name": "LD Organics Product N. 27"
    },
    {
        "coords": [-17.654491, -117.520752],
        "description": "On the brick wall right next the balcony",
        "image_url": "",
        "video_id": "UtroQkgbPnQ",
        "video_timestamp": 1174,
        "display_name": "LD Organics Product N. 28"
    },
    {
        "coords": [-16.69934, -125.024414],
        "description": "On the cylindrical sculpture",
        "image_url": "",
        "video_id": "UtroQkgbPnQ",
        "video_timestamp": 1213,
        "display_name": "LD Organics Product N. 29"
    },
    {
        "coords": [-8.559294, -129.968262],
        "description": "On the washbasin inside the public toilet",
        "image_url": "",
        "video_id": "UtroQkgbPnQ",
        "video_timestamp": 1249,
        "display_name": "LD Organics Product N. 30"
    },
    {
        "coords": [3.118576, -130.737305],
        "description": "Next to the house's side door",
        "image_url": "",
        "video_id": "UtroQkgbPnQ",
        "video_timestamp": 1284,
        "display_name": "LD Organics Product N. 31"
    },
    {
        "coords": [11.135287, -127.243652],
        "description": "Inside the hut",
        "image_url": "",
        "video_id": "UtroQkgbPnQ",
        "video_timestamp": 1321,
        "display_name": "LD Organics Product N. 32"
    },
    {
        "coords": [4.631179, -122.475586],
        "description": "On the brick wall for the plants",
        "image_url": "",
        "video_id": "UtroQkgbPnQ",
        "video_timestamp": 1364,
        "display_name": "LD Organics Product N. 33"
    },
    {
        "coords": [5.036227, -113.983154],
        "description": "On the wide flower pot next to the atm",
        "image_url": "",
        "video_id": "UtroQkgbPnQ",
        "video_timestamp": 1403,
        "display_name": "LD Organics Product N. 34"
    },
    {
        "coords": [5.692516, -103.062744],
        "description": "Inside the underground metro",
        "image_url": "",
        "video_id": "UtroQkgbPnQ",
        "video_timestamp": 1442,
        "display_name": "LD Organics Product N. 35"
    },
    {
        "coords": [6.817353, -95.08667],
        "description": "In the house's empty pot, right under the window in the backyard",
        "image_url": "",
        "video_id": "UtroQkgbPnQ",
        "video_timestamp": 1505,
        "display_name": "LD Organics Product N. 36"
    },
    {
        "coords": [9.838979, -77.420654],
        "description": "On the metal furniture next to the couch",
        "image_url": "",
        "video_id": "UtroQkgbPnQ",
        "video_timestamp": 1545,
        "display_name": "LD Organics Product N. 37"
    },
    {
        "coords": [13.336175, -78.145752],
        "description": "In the staff only kitchen area on the roof",
        "image_url": "",
        "video_id": "UtroQkgbPnQ",
        "video_timestamp": 1582,
        "display_name": "LD Organics Product N. 38"
    },
    {
        "coords": [15.739388, -82.122803],
        "description": "On the C of the CNT logo",
        "image_url": "",
        "video_id": "UtroQkgbPnQ",
        "video_timestamp": 1629,
        "display_name": "LD Organics Product N. 39"
    },
    {
        "coords": [14.4134, -92.208252],
        "description": "On the metal shelving in the parking lot",
        "image_url": "",
        "video_id": "UtroQkgbPnQ",
        "video_timestamp": 1669,
        "display_name": "LD Organics Product N. 40"
    },
    {
        "coords": [13.464422, -98.22876],
        "description": "In the small alleyway between the building and the brick wall",
        "image_url": "",
        "video_id": "UtroQkgbPnQ",
        "video_timestamp": 1710,
        "display_name": "LD Organics Product N. 41"
    },
    {
        "coords": [13.090231, -110.620301],
        "description": "On the lower roof of the Epsilon Program building, on the edge",
        "image_url": "",
        "video_id": "UtroQkgbPnQ",
        "video_timestamp": 1754,
        "display_name": "LD Organics Product N. 42"
    },
    {
        "coords": [14.466596, -117.25708],
        "description": "On the brick wall next to the pool",
        "image_url": "",
        "video_id": "UtroQkgbPnQ",
        "video_timestamp": 1805,
        "display_name": "LD Organics Product N. 43"
    },
    {
        "coords": [17.476432, -105.732422],
        "description": "On the brick wall on the small balcony up the stairs",
        "image_url": "",
        "video_id": "UtroQkgbPnQ",
        "video_timestamp": 1850,
        "display_name": "LD Organics Product N. 44"
    },
    {
        "coords": [22.816694, -104.458008],
        "description": "On the brick wall under the black umbrella",
        "image_url": "",
        "video_id": "UtroQkgbPnQ",
        "video_timestamp": 1892,
        "display_name": "LD Organics Product N. 45"
    },
    {
        "coords": [25.075648, -112.368164],
        "description": "On the wood pile inside the construction site",
        "image_url": "",
        "video_id": "UtroQkgbPnQ",
        "video_timestamp": 1937,
        "display_name": "LD Organics Product N. 46"
    },
    {
        "coords": [22.867318, -126.079102],
        "description": "On the window of the smaller house",
        "image_url": "",
        "video_id": "UtroQkgbPnQ",
        "video_timestamp": 1987,
        "display_name": "LD Organics Product N. 47"
    },
    {
        "coords": [26.961246, -129.034424],
        "description": "On the flower pot for the small tree",
        "image_url": "",
        "video_id": "UtroQkgbPnQ",
        "video_timestamp": 2032,
        "display_name": "LD Organics Product N. 48"
    },
    {
        "coords": [22.22809, -137.93335],
        "description": "On the laid flat tree trunk",
        "image_url": "",
        "video_id": "UtroQkgbPnQ",
        "video_timestamp": 2073,
        "display_name": "LD Organics Product N. 49"
    },
    {
        "coords": [12.329269, -156.687012],
        "description": "On the counter for the food stand",
        "image_url": "",
        "video_id": "UtroQkgbPnQ",
        "video_timestamp": 2115,
        "display_name": "LD Organics Product N. 50"
    },
    {
        "coords": [24.47715, -158.917236],
        "description": "At the base of the pillar",
        "image_url": "",
        "video_id": "UtroQkgbPnQ",
        "video_timestamp": 2154,
        "display_name": "LD Organics Product N. 51"
    },
    {
        "coords": [32.298934, -161.840257],
        "description": "At the base of the pillar that holds the house up",
        "image_url": "",
        "video_id": "UtroQkgbPnQ",
        "video_timestamp": 2189,
        "display_name": "LD Organics Product N. 52"
    },
    {
        "coords": [44.253069, -149.776611],
        "description": "On the flower pot for the small tree",
        "image_url": "",
        "video_id": "UtroQkgbPnQ",
        "video_timestamp": 2229,
        "display_name": "LD Organics Product N. 53"
    },
    {
        "coords": [46.445427, -134.714355],
        "description": "On the back of the sign, hidden by the bushes",
        "image_url": "",
        "video_id": "UtroQkgbPnQ",
        "video_timestamp": 2271,
        "display_name": "LD Organics Product N. 54"
    },
    {
        "coords": [32.49123, -106.402588],
        "description": "Inside of the trash can past the stairs",
        "image_url": "",
        "video_id": "UtroQkgbPnQ",
        "video_timestamp": 2308,
        "display_name": "LD Organics Product N. 55"
    },
    {
        "coords": [26.824071, -101.052246],
        "description": "On the bench",
        "image_url": "",
        "video_id": "UtroQkgbPnQ",
        "video_timestamp": 2347,
        "display_name": "LD Organics Product N. 56"
    },
    {
        "coords": [32.110496, -94.108887],
        "description": "On the brick wall at the back of the auditorium",
        "image_url": "",
        "video_id": "UtroQkgbPnQ",
        "video_timestamp": 2380,
        "display_name": "LD Organics Product N. 57"
    },
    {
        "coords": [29.52567, -90.307617],
        "description": "On the stone wall next to the banquettes",
        "image_url": "",
        "video_id": "UtroQkgbPnQ",
        "video_timestamp": 2422,
        "display_name": "LD Organics Product N. 58"
    },
    {
        "coords": [35.263562, -83.880615],
        "description": "Inbetween the wood sheets of the wooden pile",
        "image_url": "",
        "video_id": "UtroQkgbPnQ",
        "video_timestamp": 2457,
        "display_name": "LD Organics Product N. 59"
    },
    {
        "coords": [32.119801, -67.807617],
        "description": "On the bench",
        "image_url": "",
        "video_id": "UtroQkgbPnQ",
        "video_timestamp": 2498,
        "display_name": "LD Organics Product N. 60"
    },
    {
        "coords": [44.715514, -72.817383],
        "description": "Behind the rusty bobcat bucket",
        "image_url": "",
        "video_id": "UtroQkgbPnQ",
        "video_timestamp": 2534,
        "display_name": "LD Organics Product N. 61"
    },
    {
        "coords": [52.066, -76.838379],
        "description": "On the pipes laid flat at the ground floor",
        "image_url": "",
        "video_id": "UtroQkgbPnQ",
        "video_timestamp": 2575,
        "display_name": "LD Organics Product N. 62"
    },
    {
        "coords": [45.236218, -97.77832],
        "description": "On top of the barbeque",
        "image_url": "",
        "video_id": "UtroQkgbPnQ",
        "video_timestamp": 2610,
        "display_name": "LD Organics Product N. 63"
    },
    {
        "coords": [55.943048, -96.295166],
        "description": "On the window of the gas station",
        "image_url": "",
        "video_id": "UtroQkgbPnQ",
        "video_timestamp": 2651,
        "display_name": "LD Organics Product N. 64"
    },
    {
        "coords": [57.04073, -86.341553],
        "description": "On the base of the oil extractor",
        "image_url": "",
        "video_id": "UtroQkgbPnQ",
        "video_timestamp": 2685,
        "display_name": "LD Organics Product N. 65"
    },
    {
        "coords": [58.326799, -70.762939],
        "description": "On the rock, past the bushes",
        "image_url": "",
        "video_id": "UtroQkgbPnQ",
        "video_timestamp": 2726,
        "display_name": "LD Organics Product N. 66"
    },
    {
        "coords": [61.48076, -62.402344],
        "description": "Inside the hangar, on some shelving",
        "image_url": "",
        "video_id": "UtroQkgbPnQ",
        "video_timestamp": 2768,
        "display_name": "LD Organics Product N. 67"
    },
    {
        "coords": [54.394264, -64.432928],
        "description": "On an airvent on the roof",
        "image_url": "",
        "video_id": "UtroQkgbPnQ",
        "video_timestamp": 2806,
        "display_name": "LD Organics Product N. 68"
    },
    {
        "coords": [62.870179, -43.4729],
        "description": "On an airvent on the roof",
        "image_url": "",
        "video_id": "UtroQkgbPnQ",
        "video_timestamp": 2848,
        "display_name": "LD Organics Product N. 69"
    },
    {
        "coords": [66.652977, -61.710205],
        "description": "On the broken washing machine in the backyard of the house",
        "image_url": "",
        "video_id": "UtroQkgbPnQ",
        "video_timestamp": 2887,
        "display_name": "LD Organics Product N. 70"
    },
    {
        "coords": [64.024122, -95.20752],
        "description": "On the ride or die trailer",
        "image_url": "",
        "video_id": "UtroQkgbPnQ",
        "video_timestamp": 2924,
        "display_name": "LD Organics Product N. 71"
    },
    {
        "coords": [65.357677, -95.855713],
        "description": "On the wooden shelving next to the trailer",
        "image_url": "",
        "video_id": "UtroQkgbPnQ",
        "video_timestamp": 2962,
        "display_name": "LD Organics Product N. 72"
    },
    {
        "coords": [64.081805, -101.513672],
        "description": "On the small bridge of the train tracks",
        "image_url": "",
        "video_id": "UtroQkgbPnQ",
        "video_timestamp": 2996,
        "display_name": "LD Organics Product N. 73"
    },
    {
        "coords": [58.745407, -129.1333],
        "description": "In the horizontal pipe that's cut in half",
        "image_url": "",
        "video_id": "UtroQkgbPnQ",
        "video_timestamp": 3036,
        "display_name": "LD Organics Product N. 74"
    },
    {
        "coords": [61.53317, -135.933838],
        "description": "Inside the small fort made with sandbags",
        "image_url": "",
        "video_id": "UtroQkgbPnQ",
        "video_timestamp": 3077,
        "display_name": "LD Organics Product N. 75"
    },
    {
        "coords": [64.254141, -147.293701],
        "description": "Between the fruits of the greengrocer",
        "image_url": "",
        "video_id": "UtroQkgbPnQ",
        "video_timestamp": 3116,
        "display_name": "LD Organics Product N. 76"
    },
    {
        "coords": [69.065403, -141.137644],
        "description": "Laid on a small pipe in the back of the building",
        "image_url": "",
        "video_id": "UtroQkgbPnQ",
        "video_timestamp": 3151,
        "display_name": "LD Organics Product N. 77"
    },
    {
        "coords": [75.258649, -129.331055],
        "description": "At the end of the railing on the right-hand side",
        "image_url": "",
        "video_id": "UtroQkgbPnQ",
        "video_timestamp": 3190,
        "display_name": "LD Organics Product N. 78"
    },
    {
        "coords": [73.609125, -120.174241],
        "description": "On the wooden ridge under the stairs of the house",
        "image_url": "",
        "video_id": "UtroQkgbPnQ",
        "video_timestamp": 3230,
        "display_name": "LD Organics Product N. 79"
    },
    {
        "coords": [75.785942, -108.81958],
        "description": "On the ran down forklift",
        "image_url": "",
        "video_id": "UtroQkgbPnQ",
        "video_timestamp": 3270,
        "display_name": "LD Organics Product N. 80"
    },
    {
        "coords": [79.687184, -103.886719],
        "description": "On the house's loft",
        "image_url": "",
        "video_id": "UtroQkgbPnQ",
        "video_timestamp": 3311,
        "display_name": "LD Organics Product N. 81"
    },
    {
        "coords": [80.386396, -97.459717],
        "description": "On the airvent on the green roof",
        "image_url": "",
        "video_id": "UtroQkgbPnQ",
        "video_timestamp": 3363,
        "display_name": "LD Organics Product N. 82"
    },
    {
        "coords": [80.258969, -88.439941],
        "description": "On the upper floor of the farm, on some hay bales",
        "image_url": "",
        "video_id": "UtroQkgbPnQ",
        "video_timestamp": 3400,
        "display_name": "LD Organics Product N. 83"
    },
    {
        "coords": [79.866501, -68.525067],
        "description": "Inside the `SOCIAL JUSTICE FOR ALL` tent, next to the cooking pot",
        "image_url": "",
        "video_id": "UtroQkgbPnQ",
        "video_timestamp": 3445,
        "display_name": "LD Organics Product N. 84"
    },
    {
        "coords": [79.958534, -37.505863],
        "description": "On the rock formations on the small beach",
        "image_url": "",
        "video_id": "UtroQkgbPnQ",
        "video_timestamp": 3487,
        "display_name": "LD Organics Product N. 85"
    },
    {
        "coords": [76.494688, -28.058746],
        "description": "In between the tree branches",
        "image_url": "",
        "video_id": "UtroQkgbPnQ",
        "video_timestamp": 3524,
        "display_name": "LD Organics Product N. 86"
    },
    {
        "coords": [76.870796, -53.360596],
        "description": "On the metal shelving in the hut",
        "image_url": "",
        "video_id": "UtroQkgbPnQ",
        "video_timestamp": 3563,
        "display_name": "LD Organics Product N. 87"
    },
    {
        "coords": [72.666136, -54.404297],
        "description": "On the metal shelving inside the hangar, on its left hand side",
        "image_url": "",
        "video_id": "UtroQkgbPnQ",
        "video_timestamp": 3601,
        "display_name": "LD Organics Product N. 88"
    },
    {
        "coords": [69.461584, -69.547995],
        "description": "On the broken engine under the small roof",
        "image_url": "",
        "video_id": "UtroQkgbPnQ",
        "video_timestamp": 3637,
        "display_name": "LD Organics Product N. 89"
    },
    {
        "coords": [68.171555, -82.935791],
        "description": "Down the staircase of the small pier",
        "image_url": "",
        "video_id": "UtroQkgbPnQ",
        "video_timestamp": 3676,
        "display_name": "LD Organics Product N. 90"
    },
    {
        "coords": [70.399978, -90.53833],
        "description": "On the rock",
        "image_url": "",
        "video_id": "UtroQkgbPnQ",
        "video_timestamp": 3725,
        "display_name": "LD Organics Product N. 91"
    },
    {
        "coords": [76.950415, -87.451172],
        "description": "On one of the stone pillars for the Mount Chiliad Tourist Board",
        "image_url": "",
        "video_id": "UtroQkgbPnQ",
        "video_timestamp": 3764,
        "display_name": "LD Organics Product N. 92"
    },
    {
        "coords": [70.801366, -20.830078],
        "description": "On the wooden base of the house",
        "image_url": "",
        "video_id": "UtroQkgbPnQ",
        "video_timestamp": 3799,
        "display_name": "LD Organics Product N. 93"
    },
    {
        "coords": [64.235045, -25.158691],
        "description": "On the horizontal metal pipe next to the small metal bridge",
        "image_url": "",
        "video_id": "UtroQkgbPnQ",
        "video_timestamp": 3835,
        "display_name": "LD Organics Product N. 94"
    },
    {
        "coords": [55.943048, -44.604492],
        "description": "On the cement base for the green tanks",
        "image_url": "",
        "video_id": "UtroQkgbPnQ",
        "video_timestamp": 3880,
        "display_name": "LD Organics Product N. 95"
    },
    {
        "coords": [54.278055, -46.362305],
        "description": "On the back of the small hut, near the fencing",
        "image_url": "",
        "video_id": "UtroQkgbPnQ",
        "video_timestamp": 3919,
        "display_name": "LD Organics Product N. 96"
    },
    {
        "coords": [40.871988, -44.219971],
        "description": "Inside the security cabin",
        "image_url": "",
        "video_id": "UtroQkgbPnQ",
        "video_timestamp": 3955,
        "display_name": "LD Organics Product N. 97"
    },
    {
        "coords": [3.370856, -47.175293],
        "description": "On the truck trailer under the small roof",
        "image_url": "",
        "video_id": "UtroQkgbPnQ",
        "video_timestamp": 3993,
        "display_name": "LD Organics Product N. 98"
    },
    {
        "coords": [22.776182, -59.227295],
        "description": "On the electrical panel past the brick wall of the parking lot",
        "image_url": "",
        "video_id": "UtroQkgbPnQ",
        "video_timestamp": 4037,
        "display_name": "LD Organics Product N. 99"
    },
    {
        "coords": [11.40164, -63.917605],
        "description": "At the base of the tower, near the blue ladder",
        "image_url": "",
        "video_id": "UtroQkgbPnQ",
        "video_timestamp": 4071,
        "display_name": "LD Organics Product N. 100"
    }
]