[
    {
        "coords": [0,0],
        "description": "",
        "image_url": "",
        "video_id": "Ea844GlzcUs",
        "video_timestamp": 21,
        "display_name": "Signal Jammer N. 1"
    },
    {
        "coords": [0,0],
        "description": "",
        "image_url": "",
        "video_id": "Ea844GlzcUs",
        "video_timestamp": 58,
        "display_name": "Signal Jammer N. 2"
    },
    {
        "coords": [0,0],
        "description": "",
        "image_url": "",
        "video_id": "Ea844GlzcUs",
        "video_timestamp": 89,
        "display_name": "Signal Jammer N. 3"
    },
    {
        "coords": [0,0],
        "description": "",
        "image_url": "",
        "video_id": "Ea844GlzcUs",
        "video_timestamp": 113,
        "display_name": "Signal Jammer N. 4"
    },
    {
        "coords": [0,0],
        "description": "",
        "image_url": "",
        "video_id": "Ea844GlzcUs",
        "video_timestamp": 147,
        "display_name": "Signal Jammer N. 5"
    },
    {
        "coords": [0,0],
        "description": "",
        "image_url": "",
        "video_id": "Ea844GlzcUs",
        "video_timestamp": 185,
        "display_name": "Signal Jammer N. 6"
    },
    {
        "coords": [0,0],
        "description": "",
        "image_url": "",
        "video_id": "Ea844GlzcUs",
        "video_timestamp": 213,
        "display_name": "Signal Jammer N. 7"
    },
    {
        "coords": [0,0],
        "description": "",
        "image_url": "",
        "video_id": "Ea844GlzcUs",
        "video_timestamp": 248,
        "display_name": "Signal Jammer N. 8"
    },
    {
        "coords": [0,0],
        "description": "",
        "image_url": "",
        "video_id": "Ea844GlzcUs",
        "video_timestamp": 274,
        "display_name": "Signal Jammer N. 9"
    },
    {
        "coords": [0,0],
        "description": "",
        "image_url": "",
        "video_id": "Ea844GlzcUs",
        "video_timestamp": 306,
        "display_name": "Signal Jammer N. 10"
    },
    {
        "coords": [0,0],
        "description": "",
        "image_url": "",
        "video_id": "Ea844GlzcUs",
        "video_timestamp": 332,
        "display_name": "Signal Jammer N. 11"
    },
    {
        "coords": [0,0],
        "description": "",
        "image_url": "",
        "video_id": "Ea844GlzcUs",
        "video_timestamp": 362,
        "display_name": "Signal Jammer N. 12"
    },
    {
        "coords": [0,0],
        "description": "",
        "image_url": "",
        "video_id": "Ea844GlzcUs",
        "video_timestamp": 393,
        "display_name": "Signal Jammer N. 13"
    },
    {
        "coords": [0,0],
        "description": "",
        "image_url": "",
        "video_id": "Ea844GlzcUs",
        "video_timestamp": 425,
        "display_name": "Signal Jammer N. 14"
    },
    {
        "coords": [0,0],
        "description": "",
        "image_url": "",
        "video_id": "Ea844GlzcUs",
        "video_timestamp": 456,
        "display_name": "Signal Jammer N. 15"
    },
    {
        "coords": [0,0],
        "description": "",
        "image_url": "",
        "video_id": "Ea844GlzcUs",
        "video_timestamp": 486,
        "display_name": "Signal Jammer N. 16"
    },
    {
        "coords": [0,0],
        "description": "",
        "image_url": "",
        "video_id": "Ea844GlzcUs",
        "video_timestamp": 510,
        "display_name": "Signal Jammer N. 17"
    },
    {
        "coords": [0,0],
        "description": "",
        "image_url": "",
        "video_id": "Ea844GlzcUs",
        "video_timestamp": 535,
        "display_name": "Signal Jammer N. 18"
    },
    {
        "coords": [0,0],
        "description": "",
        "image_url": "",
        "video_id": "Ea844GlzcUs",
        "video_timestamp": 567,
        "display_name": "Signal Jammer N. 19"
    },
    {
        "coords": [0,0],
        "description": "",
        "image_url": "",
        "video_id": "Ea844GlzcUs",
        "video_timestamp": 594,
        "display_name": "Signal Jammer N. 20"
    },
    {
        "coords": [0,0],
        "description": "",
        "image_url": "",
        "video_id": "Ea844GlzcUs",
        "video_timestamp": 624,
        "display_name": "Signal Jammer N. 21"
    },
    {
        "coords": [0,0],
        "description": "",
        "image_url": "",
        "video_id": "Ea844GlzcUs",
        "video_timestamp": 655,
        "display_name": "Signal Jammer N. 22"
    },
    {
        "coords": [0,0],
        "description": "",
        "image_url": "",
        "video_id": "Ea844GlzcUs",
        "video_timestamp": 689,
        "display_name": "Signal Jammer N. 23"
    },
    {
        "coords": [0,0],
        "description": "",
        "image_url": "",
        "video_id": "Ea844GlzcUs",
        "video_timestamp": 717,
        "display_name": "Signal Jammer N. 24"
    },
    {
        "coords": [0,0],
        "description": "",
        "image_url": "",
        "video_id": "Ea844GlzcUs",
        "video_timestamp": 747,
        "display_name": "Signal Jammer N. 25"
    },
    {
        "coords": [0,0],
        "description": "",
        "image_url": "",
        "video_id": "Ea844GlzcUs",
        "video_timestamp": 775,
        "display_name": "Signal Jammer N. 26"
    },
    {
        "coords": [0,0],
        "description": "",
        "image_url": "",
        "video_id": "Ea844GlzcUs",
        "video_timestamp": 0,
        "display_name": "Signal Jammer N. 27"
    },
    {
        "coords": [0,0],
        "description": "",
        "image_url": "",
        "video_id": "Ea844GlzcUs",
        "video_timestamp": 841,
        "display_name": "Signal Jammer N. 28"
    },
    {
        "coords": [0,0],
        "description": "",
        "image_url": "",
        "video_id": "Ea844GlzcUs",
        "video_timestamp": 872,
        "display_name": "Signal Jammer N. 29"
    },
    {
        "coords": [0,0],
        "description": "",
        "image_url": "",
        "video_id": "Ea844GlzcUs",
        "video_timestamp": 904,
        "display_name": "Signal Jammer N. 30"
    },
    {
        "coords": [0,0],
        "description": "",
        "image_url": "",
        "video_id": "Ea844GlzcUs",
        "video_timestamp": 937,
        "display_name": "Signal Jammer N. 31"
    },
    {
        "coords": [0,0],
        "description": "",
        "image_url": "",
        "video_id": "Ea844GlzcUs",
        "video_timestamp": 969,
        "display_name": "Signal Jammer N. 32"
    },
    {
        "coords": [0,0],
        "description": "",
        "image_url": "",
        "video_id": "Ea844GlzcUs",
        "video_timestamp": 996,
        "display_name": "Signal Jammer N. 33"
    },
    {
        "coords": [0,0],
        "description": "",
        "image_url": "",
        "video_id": "Ea844GlzcUs",
        "video_timestamp": 1031,
        "display_name": "Signal Jammer N. 34"
    },
    {
        "coords": [0,0],
        "description": "",
        "image_url": "",
        "video_id": "Ea844GlzcUs",
        "video_timestamp": 1063,
        "display_name": "Signal Jammer N. 35"
    },
    {
        "coords": [0,0],
        "description": "",
        "image_url": "",
        "video_id": "Ea844GlzcUs",
        "video_timestamp": 1099,
        "display_name": "Signal Jammer N. 36"
    },
    {
        "coords": [0,0],
        "description": "",
        "image_url": "",
        "video_id": "Ea844GlzcUs",
        "video_timestamp": 1126,
        "display_name": "Signal Jammer N. 37"
    },
    {
        "coords": [0,0],
        "description": "",
        "image_url": "",
        "video_id": "Ea844GlzcUs",
        "video_timestamp": 1162,
        "display_name": "Signal Jammer N. 38"
    },
    {
        "coords": [0,0],
        "description": "",
        "image_url": "",
        "video_id": "Ea844GlzcUs",
        "video_timestamp": 1198,
        "display_name": "Signal Jammer N. 39"
    },
    {
        "coords": [0,0],
        "description": "",
        "image_url": "",
        "video_id": "Ea844GlzcUs",
        "video_timestamp": 1238,
        "display_name": "Signal Jammer N. 40"
    },
    {
        "coords": [0,0],
        "description": "",
        "image_url": "",
        "video_id": "Ea844GlzcUs",
        "video_timestamp": 1269,
        "display_name": "Signal Jammer N. 41"
    },
    {
        "coords": [0,0],
        "description": "",
        "image_url": "",
        "video_id": "Ea844GlzcUs",
        "video_timestamp": 1294,
        "display_name": "Signal Jammer N. 42"
    },
    {
        "coords": [0,0],
        "description": "",
        "image_url": "",
        "video_id": "Ea844GlzcUs",
        "video_timestamp": 1322,
        "display_name": "Signal Jammer N. 43"
    },
    {
        "coords": [0,0],
        "description": "",
        "image_url": "",
        "video_id": "Ea844GlzcUs",
        "video_timestamp": 1350,
        "display_name": "Signal Jammer N. 44"
    },
    {
        "coords": [0,0],
        "description": "",
        "image_url": "",
        "video_id": "Ea844GlzcUs",
        "video_timestamp": 1384,
        "display_name": "Signal Jammer N. 45"
    },
    {
        "coords": [0,0],
        "description": "",
        "image_url": "",
        "video_id": "Ea844GlzcUs",
        "video_timestamp": 1410,
        "display_name": "Signal Jammer N. 46"
    },
    {
        "coords": [0,0],
        "description": "",
        "image_url": "",
        "video_id": "Ea844GlzcUs",
        "video_timestamp": 1440,
        "display_name": "Signal Jammer N. 47"
    },
    {
        "coords": [0,0],
        "description": "",
        "image_url": "",
        "video_id": "Ea844GlzcUs",
        "video_timestamp": 1472,
        "display_name": "Signal Jammer N. 48"
    },
    {
        "coords": [0,0],
        "description": "",
        "image_url": "",
        "video_id": "Ea844GlzcUs",
        "video_timestamp": 1501,
        "display_name": "Signal Jammer N. 49"
    },
    {
        "coords": [0,0],
        "description": "",
        "image_url": "",
        "video_id": "Ea844GlzcUs",
        "video_timestamp": 1534,
        "display_name": "Signal Jammer N. 50"
    }
]